rcdsa-0.24.0.dist-info/METADATA
rcdsa-0.24.0.dist-info/WHEEL
rcdsa-0.24.0.dist-info/entry_points.txt
rcdsa-0.24.0.dist-info/licenses/LICENSE
rcdsa/__init__.py
rcdsa/algorithm/__init__.py
rcdsa/algorithm/graph/__init__.py
rcdsa/algorithm/graph/all_topo_sort.py
rcdsa/algorithm/graph/bellman_ford.py
rcdsa/algorithm/graph/boruvka_mst.py
rcdsa/algorithm/graph/cycle_detecte.py
rcdsa/algorithm/graph/dijkstra.py
rcdsa/algorithm/graph/floyd_warshall.py
rcdsa/algorithm/graph/johnson.py
rcdsa/algorithm/graph/kruskal_mst.py
rcdsa/algorithm/graph/prim_mst.py
rcdsa/algorithm/graph/topo_sort.py
rcdsa/algorithm/search/__init__.py
rcdsa/algorithm/search/binary_search.py
rcdsa/algorithm/search/linear_search.py
rcdsa/algorithm/sort/__init__.py
rcdsa/algorithm/sort/bubble_sort.py
rcdsa/algorithm/sort/heap_sort.py
rcdsa/algorithm/sort/insertion_sort.py
rcdsa/algorithm/sort/merge_sort.py
rcdsa/algorithm/sort/quick_sort.py
rcdsa/algorithm/sort/selection_sort.py
rcdsa/datastruct/__init__.py
rcdsa/datastruct/graph/graph.py
rcdsa/datastruct/graph/stable_graph.py
rcdsa/datastruct/hash/hash_map.py
rcdsa/datastruct/hash/hash_set.py
rcdsa/datastruct/hash/hash_table.py
rcdsa/datastruct/hash/linked_hash_map.py
rcdsa/datastruct/hash/linked_hash_set.py
rcdsa/datastruct/hash/linked_hash_table.py
rcdsa/datastruct/list/linked_list.py
rcdsa/datastruct/queue/array_queue.py
rcdsa/datastruct/queue/linked_queue.py
rcdsa/datastruct/stack/array_stack.py
rcdsa/datastruct/stack/linked_stack.py
rcdsa/datastruct/tree/avl_tree.py
rcdsa/datastruct/tree/binary_search_tree.py
rcdsa/datastruct/tree/binary_tree.py
rcdsa/datastruct/tree/heap.py
rcdsa/datastruct/tree/red_black_tree.py
rcdsa/datastruct/tree/tree.py
rcdsa/datastruct/tree/union_find_set.py
rcdsa-0.24.0.dist-info/RECORD
