Metadata-Version: 2.4
Name: rcdsa
Version: 0.24.0
Summary: ✨yep, a datastruct and algorithm toolkit written in python.
Author-Email: rubitcat <rubitcat@outlook.com>
License-Expression: MIT
License-File: LICENSE
Classifier: Programming Language :: Python :: 3
Classifier: Operating System :: OS Independent
Project-URL: Homepage, https://rubitcat.cn/docsec/docs/software/datastruct-algorithm/algorithm-overview/
Project-URL: Issues, https://github.com/rubitcat/rcdsa-python/issues
Requires-Python: >=3.8
